[{"record_number":"896772","transcript_pages":[{"uri":"http://transcripts.sl.nsw.gov.au/api/entity_node/273152","id":"273152","resource":"node"},{"uri":"http://transcripts.sl.nsw.gov.au/api/entity_node/273153","id":"273153","resource":"node"},{"uri":"http://transcripts.sl.nsw.gov.au/api/entity_node/273154","id":"273154","resource":"node"},{"uri":"http://transcripts.sl.nsw.gov.au/api/entity_node/273155","id":"273155","resource":"node"},{"uri":"http://transcripts.sl.nsw.gov.au/api/entity_node/273156","id":"273156","resource":"node"},{"uri":"http://transcripts.sl.nsw.gov.au/api/entity_node/273157","id":"273157","resource":"node"},{"uri":"http://transcripts.sl.nsw.gov.au/api/entity_node/273158","id":"273158","resource":"node"},{"uri":"http://transcripts.sl.nsw.gov.au/api/entity_node/273159","id":"273159","resource":"node"},{"uri":"http://transcripts.sl.nsw.gov.au/api/entity_node/273160","id":"273160","resource":"node"}],"percentage_unlocked":"0","nid":"272568","title":"Item 74: Letters smuggled out of Holsworthy Internment Camp, March 1919"}]