[{"record_number":"991175","transcript_pages":[{"uri":"http://transcripts.sl.nsw.gov.au/api/entity_node/334424","id":"334424","resource":"node"},{"uri":"http://transcripts.sl.nsw.gov.au/api/entity_node/334433","id":"334433","resource":"node"},{"uri":"http://transcripts.sl.nsw.gov.au/api/entity_node/334434","id":"334434","resource":"node"},{"uri":"http://transcripts.sl.nsw.gov.au/api/entity_node/334435","id":"334435","resource":"node"},{"uri":"http://transcripts.sl.nsw.gov.au/api/entity_node/334436","id":"334436","resource":"node"},{"uri":"http://transcripts.sl.nsw.gov.au/api/entity_node/334437","id":"334437","resource":"node"},{"uri":"http://transcripts.sl.nsw.gov.au/api/entity_node/334438","id":"334438","resource":"node"},{"uri":"http://transcripts.sl.nsw.gov.au/api/entity_node/334439","id":"334439","resource":"node"},{"uri":"http://transcripts.sl.nsw.gov.au/api/entity_node/334440","id":"334440","resource":"node"},{"uri":"http://transcripts.sl.nsw.gov.au/api/entity_node/334441","id":"334441","resource":"node"},{"uri":"http://transcripts.sl.nsw.gov.au/api/entity_node/334442","id":"334442","resource":"node"},{"uri":"http://transcripts.sl.nsw.gov.au/api/entity_node/334425","id":"334425","resource":"node"},{"uri":"http://transcripts.sl.nsw.gov.au/api/entity_node/334443","id":"334443","resource":"node"},{"uri":"http://transcripts.sl.nsw.gov.au/api/entity_node/334444","id":"334444","resource":"node"},{"uri":"http://transcripts.sl.nsw.gov.au/api/entity_node/334445","id":"334445","resource":"node"},{"uri":"http://transcripts.sl.nsw.gov.au/api/entity_node/334446","id":"334446","resource":"node"},{"uri":"http://transcripts.sl.nsw.gov.au/api/entity_node/334447","id":"334447","resource":"node"},{"uri":"http://transcripts.sl.nsw.gov.au/api/entity_node/334448","id":"334448","resource":"node"},{"uri":"http://transcripts.sl.nsw.gov.au/api/entity_node/334426","id":"334426","resource":"node"},{"uri":"http://transcripts.sl.nsw.gov.au/api/entity_node/334427","id":"334427","resource":"node"},{"uri":"http://transcripts.sl.nsw.gov.au/api/entity_node/334428","id":"334428","resource":"node"},{"uri":"http://transcripts.sl.nsw.gov.au/api/entity_node/334429","id":"334429","resource":"node"},{"uri":"http://transcripts.sl.nsw.gov.au/api/entity_node/334430","id":"334430","resource":"node"},{"uri":"http://transcripts.sl.nsw.gov.au/api/entity_node/334431","id":"334431","resource":"node"},{"uri":"http://transcripts.sl.nsw.gov.au/api/entity_node/334432","id":"334432","resource":"node"}],"percentage_unlocked":"0","nid":"338030","title":"Stanley Dewhurst diary, 8 January-20 September 1917"}]