[{"record_number":"1045320","transcript_pages":[{"uri":"http://transcripts.sl.nsw.gov.au/api/entity_node/363613","id":"363613","resource":"node"},{"uri":"http://transcripts.sl.nsw.gov.au/api/entity_node/363622","id":"363622","resource":"node"},{"uri":"http://transcripts.sl.nsw.gov.au/api/entity_node/363712","id":"363712","resource":"node"},{"uri":"http://transcripts.sl.nsw.gov.au/api/entity_node/363713","id":"363713","resource":"node"},{"uri":"http://transcripts.sl.nsw.gov.au/api/entity_node/363714","id":"363714","resource":"node"},{"uri":"http://transcripts.sl.nsw.gov.au/api/entity_node/363715","id":"363715","resource":"node"},{"uri":"http://transcripts.sl.nsw.gov.au/api/entity_node/363716","id":"363716","resource":"node"},{"uri":"http://transcripts.sl.nsw.gov.au/api/entity_node/363717","id":"363717","resource":"node"},{"uri":"http://transcripts.sl.nsw.gov.au/api/entity_node/363718","id":"363718","resource":"node"},{"uri":"http://transcripts.sl.nsw.gov.au/api/entity_node/363719","id":"363719","resource":"node"},{"uri":"http://transcripts.sl.nsw.gov.au/api/entity_node/363720","id":"363720","resource":"node"},{"uri":"http://transcripts.sl.nsw.gov.au/api/entity_node/363721","id":"363721","resource":"node"},{"uri":"http://transcripts.sl.nsw.gov.au/api/entity_node/363623","id":"363623","resource":"node"},{"uri":"http://transcripts.sl.nsw.gov.au/api/entity_node/363722","id":"363722","resource":"node"},{"uri":"http://transcripts.sl.nsw.gov.au/api/entity_node/363723","id":"363723","resource":"node"},{"uri":"http://transcripts.sl.nsw.gov.au/api/entity_node/363724","id":"363724","resource":"node"},{"uri":"http://transcripts.sl.nsw.gov.au/api/entity_node/363725","id":"363725","resource":"node"},{"uri":"http://transcripts.sl.nsw.gov.au/api/entity_node/363726","id":"363726","resource":"node"},{"uri":"http://transcripts.sl.nsw.gov.au/api/entity_node/363727","id":"363727","resource":"node"},{"uri":"http://transcripts.sl.nsw.gov.au/api/entity_node/363728","id":"363728","resource":"node"},{"uri":"http://transcripts.sl.nsw.gov.au/api/entity_node/363729","id":"363729","resource":"node"},{"uri":"http://transcripts.sl.nsw.gov.au/api/entity_node/363730","id":"363730","resource":"node"},{"uri":"http://transcripts.sl.nsw.gov.au/api/entity_node/363731","id":"363731","resource":"node"},{"uri":"http://transcripts.sl.nsw.gov.au/api/entity_node/363624","id":"363624","resource":"node"},{"uri":"http://transcripts.sl.nsw.gov.au/api/entity_node/363732","id":"363732","resource":"node"},{"uri":"http://transcripts.sl.nsw.gov.au/api/entity_node/363733","id":"363733","resource":"node"},{"uri":"http://transcripts.sl.nsw.gov.au/api/entity_node/363734","id":"363734","resource":"node"},{"uri":"http://transcripts.sl.nsw.gov.au/api/entity_node/363735","id":"363735","resource":"node"},{"uri":"http://transcripts.sl.nsw.gov.au/api/entity_node/363736","id":"363736","resource":"node"},{"uri":"http://transcripts.sl.nsw.gov.au/api/entity_node/363737","id":"363737","resource":"node"},{"uri":"http://transcripts.sl.nsw.gov.au/api/entity_node/363738","id":"363738","resource":"node"},{"uri":"http://transcripts.sl.nsw.gov.au/api/entity_node/363739","id":"363739","resource":"node"},{"uri":"http://transcripts.sl.nsw.gov.au/api/entity_node/363740","id":"363740","resource":"node"},{"uri":"http://transcripts.sl.nsw.gov.au/api/entity_node/363741","id":"363741","resource":"node"},{"uri":"http://transcripts.sl.nsw.gov.au/api/entity_node/363625","id":"363625","resource":"node"},{"uri":"http://transcripts.sl.nsw.gov.au/api/entity_node/363742","id":"363742","resource":"node"},{"uri":"http://transcripts.sl.nsw.gov.au/api/entity_node/363743","id":"363743","resource":"node"},{"uri":"http://transcripts.sl.nsw.gov.au/api/entity_node/363744","id":"363744","resource":"node"},{"uri":"http://transcripts.sl.nsw.gov.au/api/entity_node/363745","id":"363745","resource":"node"},{"uri":"http://transcripts.sl.nsw.gov.au/api/entity_node/363746","id":"363746","resource":"node"},{"uri":"http://transcripts.sl.nsw.gov.au/api/entity_node/363747","id":"363747","resource":"node"},{"uri":"http://transcripts.sl.nsw.gov.au/api/entity_node/363748","id":"363748","resource":"node"},{"uri":"http://transcripts.sl.nsw.gov.au/api/entity_node/363749","id":"363749","resource":"node"},{"uri":"http://transcripts.sl.nsw.gov.au/api/entity_node/363750","id":"363750","resource":"node"},{"uri":"http://transcripts.sl.nsw.gov.au/api/entity_node/363751","id":"363751","resource":"node"},{"uri":"http://transcripts.sl.nsw.gov.au/api/entity_node/363626","id":"363626","resource":"node"},{"uri":"http://transcripts.sl.nsw.gov.au/api/entity_node/363752","id":"363752","resource":"node"},{"uri":"http://transcripts.sl.nsw.gov.au/api/entity_node/363753","id":"363753","resource":"node"},{"uri":"http://transcripts.sl.nsw.gov.au/api/entity_node/363754","id":"363754","resource":"node"},{"uri":"http://transcripts.sl.nsw.gov.au/api/entity_node/363755","id":"363755","resource":"node"},{"uri":"http://transcripts.sl.nsw.gov.au/api/entity_node/363756","id":"363756","resource":"node"},{"uri":"http://transcripts.sl.nsw.gov.au/api/entity_node/363627","id":"363627","resource":"node"},{"uri":"http://transcripts.sl.nsw.gov.au/api/entity_node/363628","id":"363628","resource":"node"},{"uri":"http://transcripts.sl.nsw.gov.au/api/entity_node/363629","id":"363629","resource":"node"},{"uri":"http://transcripts.sl.nsw.gov.au/api/entity_node/363630","id":"363630","resource":"node"},{"uri":"http://transcripts.sl.nsw.gov.au/api/entity_node/363631","id":"363631","resource":"node"},{"uri":"http://transcripts.sl.nsw.gov.au/api/entity_node/363614","id":"363614","resource":"node"},{"uri":"http://transcripts.sl.nsw.gov.au/api/entity_node/363632","id":"363632","resource":"node"},{"uri":"http://transcripts.sl.nsw.gov.au/api/entity_node/363633","id":"363633","resource":"node"},{"uri":"http://transcripts.sl.nsw.gov.au/api/entity_node/363634","id":"363634","resource":"node"},{"uri":"http://transcripts.sl.nsw.gov.au/api/entity_node/363635","id":"363635","resource":"node"},{"uri":"http://transcripts.sl.nsw.gov.au/api/entity_node/363636","id":"363636","resource":"node"},{"uri":"http://transcripts.sl.nsw.gov.au/api/entity_node/363637","id":"363637","resource":"node"},{"uri":"http://transcripts.sl.nsw.gov.au/api/entity_node/363638","id":"363638","resource":"node"},{"uri":"http://transcripts.sl.nsw.gov.au/api/entity_node/363639","id":"363639","resource":"node"},{"uri":"http://transcripts.sl.nsw.gov.au/api/entity_node/363640","id":"363640","resource":"node"},{"uri":"http://transcripts.sl.nsw.gov.au/api/entity_node/363641","id":"363641","resource":"node"},{"uri":"http://transcripts.sl.nsw.gov.au/api/entity_node/363615","id":"363615","resource":"node"},{"uri":"http://transcripts.sl.nsw.gov.au/api/entity_node/363642","id":"363642","resource":"node"},{"uri":"http://transcripts.sl.nsw.gov.au/api/entity_node/363643","id":"363643","resource":"node"},{"uri":"http://transcripts.sl.nsw.gov.au/api/entity_node/363644","id":"363644","resource":"node"},{"uri":"http://transcripts.sl.nsw.gov.au/api/entity_node/363645","id":"363645","resource":"node"},{"uri":"http://transcripts.sl.nsw.gov.au/api/entity_node/363646","id":"363646","resource":"node"},{"uri":"http://transcripts.sl.nsw.gov.au/api/entity_node/363647","id":"363647","resource":"node"},{"uri":"http://transcripts.sl.nsw.gov.au/api/entity_node/363648","id":"363648","resource":"node"},{"uri":"http://transcripts.sl.nsw.gov.au/api/entity_node/363649","id":"363649","resource":"node"},{"uri":"http://transcripts.sl.nsw.gov.au/api/entity_node/363650","id":"363650","resource":"node"},{"uri":"http://transcripts.sl.nsw.gov.au/api/entity_node/363651","id":"363651","resource":"node"},{"uri":"http://transcripts.sl.nsw.gov.au/api/entity_node/363616","id":"363616","resource":"node"},{"uri":"http://transcripts.sl.nsw.gov.au/api/entity_node/363652","id":"363652","resource":"node"},{"uri":"http://transcripts.sl.nsw.gov.au/api/entity_node/363653","id":"363653","resource":"node"},{"uri":"http://transcripts.sl.nsw.gov.au/api/entity_node/363654","id":"363654","resource":"node"},{"uri":"http://transcripts.sl.nsw.gov.au/api/entity_node/363655","id":"363655","resource":"node"},{"uri":"http://transcripts.sl.nsw.gov.au/api/entity_node/363656","id":"363656","resource":"node"},{"uri":"http://transcripts.sl.nsw.gov.au/api/entity_node/363657","id":"363657","resource":"node"},{"uri":"http://transcripts.sl.nsw.gov.au/api/entity_node/363658","id":"363658","resource":"node"},{"uri":"http://transcripts.sl.nsw.gov.au/api/entity_node/363659","id":"363659","resource":"node"},{"uri":"http://transcripts.sl.nsw.gov.au/api/entity_node/363660","id":"363660","resource":"node"},{"uri":"http://transcripts.sl.nsw.gov.au/api/entity_node/363661","id":"363661","resource":"node"},{"uri":"http://transcripts.sl.nsw.gov.au/api/entity_node/363617","id":"363617","resource":"node"},{"uri":"http://transcripts.sl.nsw.gov.au/api/entity_node/363662","id":"363662","resource":"node"},{"uri":"http://transcripts.sl.nsw.gov.au/api/entity_node/363663","id":"363663","resource":"node"},{"uri":"http://transcripts.sl.nsw.gov.au/api/entity_node/363664","id":"363664","resource":"node"},{"uri":"http://transcripts.sl.nsw.gov.au/api/entity_node/363665","id":"363665","resource":"node"},{"uri":"http://transcripts.sl.nsw.gov.au/api/entity_node/363666","id":"363666","resource":"node"},{"uri":"http://transcripts.sl.nsw.gov.au/api/entity_node/363667","id":"363667","resource":"node"},{"uri":"http://transcripts.sl.nsw.gov.au/api/entity_node/363668","id":"363668","resource":"node"},{"uri":"http://transcripts.sl.nsw.gov.au/api/entity_node/363669","id":"363669","resource":"node"},{"uri":"http://transcripts.sl.nsw.gov.au/api/entity_node/363670","id":"363670","resource":"node"},{"uri":"http://transcripts.sl.nsw.gov.au/api/entity_node/363671","id":"363671","resource":"node"},{"uri":"http://transcripts.sl.nsw.gov.au/api/entity_node/363618","id":"363618","resource":"node"},{"uri":"http://transcripts.sl.nsw.gov.au/api/entity_node/363672","id":"363672","resource":"node"},{"uri":"http://transcripts.sl.nsw.gov.au/api/entity_node/363673","id":"363673","resource":"node"},{"uri":"http://transcripts.sl.nsw.gov.au/api/entity_node/363674","id":"363674","resource":"node"},{"uri":"http://transcripts.sl.nsw.gov.au/api/entity_node/363675","id":"363675","resource":"node"},{"uri":"http://transcripts.sl.nsw.gov.au/api/entity_node/363676","id":"363676","resource":"node"},{"uri":"http://transcripts.sl.nsw.gov.au/api/entity_node/363677","id":"363677","resource":"node"},{"uri":"http://transcripts.sl.nsw.gov.au/api/entity_node/363678","id":"363678","resource":"node"},{"uri":"http://transcripts.sl.nsw.gov.au/api/entity_node/363679","id":"363679","resource":"node"},{"uri":"http://transcripts.sl.nsw.gov.au/api/entity_node/363680","id":"363680","resource":"node"},{"uri":"http://transcripts.sl.nsw.gov.au/api/entity_node/363681","id":"363681","resource":"node"},{"uri":"http://transcripts.sl.nsw.gov.au/api/entity_node/363619","id":"363619","resource":"node"},{"uri":"http://transcripts.sl.nsw.gov.au/api/entity_node/363682","id":"363682","resource":"node"},{"uri":"http://transcripts.sl.nsw.gov.au/api/entity_node/363683","id":"363683","resource":"node"},{"uri":"http://transcripts.sl.nsw.gov.au/api/entity_node/363684","id":"363684","resource":"node"},{"uri":"http://transcripts.sl.nsw.gov.au/api/entity_node/363685","id":"363685","resource":"node"},{"uri":"http://transcripts.sl.nsw.gov.au/api/entity_node/363686","id":"363686","resource":"node"},{"uri":"http://transcripts.sl.nsw.gov.au/api/entity_node/363687","id":"363687","resource":"node"},{"uri":"http://transcripts.sl.nsw.gov.au/api/entity_node/363688","id":"363688","resource":"node"},{"uri":"http://transcripts.sl.nsw.gov.au/api/entity_node/363689","id":"363689","resource":"node"},{"uri":"http://transcripts.sl.nsw.gov.au/api/entity_node/363690","id":"363690","resource":"node"},{"uri":"http://transcripts.sl.nsw.gov.au/api/entity_node/363691","id":"363691","resource":"node"},{"uri":"http://transcripts.sl.nsw.gov.au/api/entity_node/363620","id":"363620","resource":"node"},{"uri":"http://transcripts.sl.nsw.gov.au/api/entity_node/363692","id":"363692","resource":"node"},{"uri":"http://transcripts.sl.nsw.gov.au/api/entity_node/363693","id":"363693","resource":"node"},{"uri":"http://transcripts.sl.nsw.gov.au/api/entity_node/363694","id":"363694","resource":"node"},{"uri":"http://transcripts.sl.nsw.gov.au/api/entity_node/363695","id":"363695","resource":"node"},{"uri":"http://transcripts.sl.nsw.gov.au/api/entity_node/363696","id":"363696","resource":"node"},{"uri":"http://transcripts.sl.nsw.gov.au/api/entity_node/363697","id":"363697","resource":"node"},{"uri":"http://transcripts.sl.nsw.gov.au/api/entity_node/363698","id":"363698","resource":"node"},{"uri":"http://transcripts.sl.nsw.gov.au/api/entity_node/363699","id":"363699","resource":"node"},{"uri":"http://transcripts.sl.nsw.gov.au/api/entity_node/363700","id":"363700","resource":"node"},{"uri":"http://transcripts.sl.nsw.gov.au/api/entity_node/363701","id":"363701","resource":"node"},{"uri":"http://transcripts.sl.nsw.gov.au/api/entity_node/363621","id":"363621","resource":"node"},{"uri":"http://transcripts.sl.nsw.gov.au/api/entity_node/363702","id":"363702","resource":"node"},{"uri":"http://transcripts.sl.nsw.gov.au/api/entity_node/363703","id":"363703","resource":"node"},{"uri":"http://transcripts.sl.nsw.gov.au/api/entity_node/363704","id":"363704","resource":"node"},{"uri":"http://transcripts.sl.nsw.gov.au/api/entity_node/363705","id":"363705","resource":"node"},{"uri":"http://transcripts.sl.nsw.gov.au/api/entity_node/363706","id":"363706","resource":"node"},{"uri":"http://transcripts.sl.nsw.gov.au/api/entity_node/363707","id":"363707","resource":"node"},{"uri":"http://transcripts.sl.nsw.gov.au/api/entity_node/363708","id":"363708","resource":"node"},{"uri":"http://transcripts.sl.nsw.gov.au/api/entity_node/363709","id":"363709","resource":"node"},{"uri":"http://transcripts.sl.nsw.gov.au/api/entity_node/363710","id":"363710","resource":"node"},{"uri":"http://transcripts.sl.nsw.gov.au/api/entity_node/363711","id":"363711","resource":"node"}],"percentage_unlocked":"0","nid":"365786","title":"Item 05: Irene Victoria Read talks on Egypt and conscription, 1915-1916"}]