{"vid":"106678","uid":"1","title":"John H. Wheat narrative, ca. 1914-1918 - Page 13","log":"Created by FeedsNodeProcessor","status":"1","comment":"1","promote":"0","sticky":"0","ds_switch":"","nid":"106655","type":"transcript_page","language":"und","created":"1389071704","changed":"1397710081","tnid":"0","translate":"0","revision_timestamp":"1397710081","revision_uid":"0","field_page_completed":{"und":[{"value":"6"}]},"field_transcription":{"und":[{"value":"<a name=\"a3901013\"></a></p>\r\n\r\n<p>[Page 13]<br>\r\nWe arrived Malta 21st March.  23rd March we go into Dock and it was found necessary to put 13 new plates on the bottom.  April 9th the submarine depot ship Adamant arrived with submarines E 11, 14 and 15.</p>\r\n\r\n<p>The following day they left for the Dardanelles. We came out of dock April 16th.  April 18th we go outside the harbour for a trial run everything is satisfactory.  We leave for Lemnos the same evening.  After a fairly good trip we arrive Lemnos April 22nd and go alongside the Adamant.  The following day we <strike>were</strike> fall in on the upper deck of the Adamant while the Captain of the Adamant read out a recommendation from the Admiralty on AE 11's good work, both for record steaming and for escorting the second contingent from Australia, only spending a few days in harbour during the 12 months she had been in commission.  In the 12 months we had steamed nearly 40,000 miles.  He finished up by saying that we were recommended for 7 days leave at the first opportunity.</p>\r\n\r\n<p>After this we were ordered to get in one month's provisions and be ready to proceed by 2 p.m. the same day.  By this order we had a good idea where we were going (Dardanelles).  After taking in provisions we cast off from the Adamant at 2 p.m., and lay off from the battleship Queen Elizabeth while a wireless officer came off to inspect our wireless to see that it was correct: then we proceeded to Tenedos arriving there 6.30 a.m. 23rd April.<br>\r\nAfter a short trial dive we went alongside the Swiftsure and made fast, we took in some more provisions which we could not get from the Adamant.  We then had sufficient food to last us <strike>from</strike> for a month <strike>to</strike> or 6 weeks.  We then knew that we were leaving that night at 1.30 a.m. to make a passage through the Dardanelles.  An honour for the small young Aust. Fleet.  We were all greatly excited and I think the majority of us had very little sleep that night: no boat had up till this time been through the Dardanelles and we did not know what dangers awaited us in the way of mines and nets etc.</p>\r\n\r\n<p>A French submarine had been sunk in attempting a passage in January 1915 and one of our submarines on April 17th 1915, so we were the third to make an attempt and the <u>first</u> to succeed.  We got through- another case of \"Aust will be there\" but didn't get back.  We cast off from the Swiftsure at 1.30 and proceed to the entrance of the Dardanelles, it being our object to get as far as we could on the surface, without being seen by the searchlights and before daylight.  On entering the Dardanelles, between Cape Helles and Kum Kale there was a small gasoline searchlight on our starboard hand.  However we got by this without being noticed.  We got about six miles inside the entrance.  The searchlights on the forts of Chanak were very bright, but they seemed to be very careless as if not expecting to see anything.  Owing to the searchlights we were forced to dive at 4.5 a.m.  At this stage a very unlucky accident happened.  our foremost hydroplane coupling broke.  This was</p>\r\n\r\n<p>\r\n","format":"plain_text","safe_value":"<p><a name=\"a3901013\"></a></p>\n<p>[Page 13]<br><br />\nWe arrived Malta 21st March.  23rd March we go into Dock and it was found necessary to put 13 new plates on the bottom.  April 9th the submarine depot ship Adamant arrived with submarines E 11, 14 and 15.</p>\n<p>The following day they left for the Dardanelles. We came out of dock April 16th.  April 18th we go outside the harbour for a trial run everything is satisfactory.  We leave for Lemnos the same evening.  After a fairly good trip we arrive Lemnos April 22nd and go alongside the Adamant.  The following day we <strike>were</strike> fall in on the upper deck of the Adamant while the Captain of the Adamant read out a recommendation from the Admiralty on AE 11's good work, both for record steaming and for escorting the second contingent from Australia, only spending a few days in harbour during the 12 months she had been in commission.  In the 12 months we had steamed nearly 40,000 miles.  He finished up by saying that we were recommended for 7 days leave at the first opportunity.</p>\n<p>After this we were ordered to get in one month's provisions and be ready to proceed by 2 p.m. the same day.  By this order we had a good idea where we were going (Dardanelles).  After taking in provisions we cast off from the Adamant at 2 p.m., and lay off from the battleship Queen Elizabeth while a wireless officer came off to inspect our wireless to see that it was correct: then we proceeded to Tenedos arriving there 6.30 a.m. 23rd April.<br><br />\nAfter a short trial dive we went alongside the Swiftsure and made fast, we took in some more provisions which we could not get from the Adamant.  We then had sufficient food to last us <strike>from</strike> for a month <strike>to</strike> or 6 weeks.  We then knew that we were leaving that night at 1.30 a.m. to make a passage through the Dardanelles.  An honour for the small young Aust. Fleet.  We were all greatly excited and I think the majority of us had very little sleep that night: no boat had up till this time been through the Dardanelles and we did not know what dangers awaited us in the way of mines and nets etc.</p>\n<p>A French submarine had been sunk in attempting a passage in January 1915 and one of our submarines on April 17th 1915, so we were the third to make an attempt and the <u>first</u> to succeed.  We got through- another case of \"Aust will be there\" but didn't get back.  We cast off from the Swiftsure at 1.30 and proceed to the entrance of the Dardanelles, it being our object to get as far as we could on the surface, without being seen by the searchlights and before daylight.  On entering the Dardanelles, between Cape Helles and Kum Kale there was a small gasoline searchlight on our starboard hand.  However we got by this without being noticed.  We got about six miles inside the entrance.  The searchlights on the forts of Chanak were very bright, but they seemed to be very careless as if not expecting to see anything.  Owing to the searchlights we were forced to dive at 4.5 a.m.  At this stage a very unlucky accident happened.  our foremost hydroplane coupling broke.  This was</p>\n<p>"}]},"field_working_notes":[],"field_transcript_image":{"und":[{"fid":"107553","uid":"0","filename":"a3901013h.jpg","uri":"public://a3901013h.jpg","filemime":"image/jpeg","filesize":"567330","status":"1","timestamp":"1389071704","type":"image","field_file_image_alt_text":[],"field_file_image_title_text":[],"metadata":{"height":1050,"width":820},"alt":"","title":"","display":"1","description":null}]},"field_diary_title":{"und":[{"value":"John H. Wheat narrative, ca. 1914-1918","format":"plain_text","safe_value":"John H. Wheat narrative, ca. 1914-1918"}]},"field_page_number":{"und":[{"value":"13"}]},"field_review_notes":[],"field_url_path":{"und":[{"value":"/page/106655/view"}]},"field_status":{"und":[{"value":"6"}]},"field_transcript_edits":[],"panelizer":{"page_manager":{"entity_type":"node","entity_id":"106655","revision_id":"106678","name":"node:transcript_page:default","no_blocks":"0","css_id":"","css":"","pipeline":"standard","contexts":[{"identifier":"User","keyword":"user","name":"user","type":"current","uid":"","id":1}],"relationships":[],"did":"0","view_mode":"page_manager","css_class":"","title_element":"H2","link_to_entity":"1","extra":[],"display":{"args":[],"content":{"73":{"pid":"73","did":"13","panel":"center","type":"entity_field","subtype":"node:transcription_document_ref","shown":"1","access":[],"configuration":{"label":"hidden","formatter":"node_reference_default","delta_limit":0,"delta_offset":"0","delta_reversed":false,"formatter_settings":[],"context":"panelizer"},"cache":[],"style":[],"css":[],"extras":[],"position":"0","locks":[],"uuid":"9ccbf756-f2b4-4d57-bbfd-7c7fa38c5a8f"},"74":{"pid":"74","did":"13","panel":"center","type":"entity_field","subtype":"node:page_weight","shown":"1","access":[],"configuration":{"label":"hidden","formatter":"text_default","delta_limit":0,"delta_offset":"0","delta_reversed":false,"formatter_settings":[],"context":"panelizer"},"cache":[],"style":[],"css":[],"extras":[],"position":"1","locks":[],"uuid":"d24dfe39-4671-47ec-be85-d537d02b50be"},"75":{"pid":"75","did":"13","panel":"center","type":"entity_field","subtype":"node:field_page_completed","shown":"1","access":[],"configuration":{"label":"above","formatter":"list_default","delta_limit":0,"delta_offset":"0","delta_reversed":false,"formatter_settings":[],"context":"panelizer"},"cache":[],"style":[],"css":[],"extras":[],"position":"2","locks":[],"uuid":"f9c3ede0-b95f-493f-9535-0a7366ece5b1"},"76":{"pid":"76","did":"13","panel":"center","type":"entity_field","subtype":"node:field_transcription","shown":"1","access":[],"configuration":{"label":"above","formatter":"text_default","delta_limit":0,"delta_offset":"0","delta_reversed":false,"formatter_settings":[],"context":"panelizer"},"cache":[],"style":[],"css":[],"extras":[],"position":"3","locks":[],"uuid":"b609cc6b-c87b-4692-9520-01c431aa0e77"},"77":{"pid":"77","did":"13","panel":"center","type":"entity_field","subtype":"node:field_working_notes","shown":"1","access":[],"configuration":{"label":"above","formatter":"text_default","delta_limit":0,"delta_offset":"0","delta_reversed":false,"formatter_settings":[],"context":"panelizer"},"cache":[],"style":[],"css":[],"extras":[],"position":"4","locks":[],"uuid":"127fb571-c17b-4a8f-8e0c-00fa63bdc743"},"78":{"pid":"78","did":"13","panel":"center","type":"entity_field","subtype":"node:field_transcript_image","shown":"1","access":[],"configuration":{"label":"above","formatter":"file_default","delta_limit":0,"delta_offset":"0","delta_reversed":false,"formatter_settings":[],"context":"panelizer"},"cache":[],"style":[],"css":[],"extras":[],"position":"5","locks":[],"uuid":"ccd0c00a-13dc-4501-a91e-34e3d2b10f67"},"79":{"pid":"79","did":"13","panel":"center","type":"node_links","subtype":"node_links","shown":"1","access":[],"configuration":{"override_title":false,"override_title_text":"","build_mode":"page_manager","identifier":"","link":true,"context":"panelizer"},"cache":[],"style":[],"css":{"css_class":"link-wrapper"},"extras":[],"position":"6","locks":[],"uuid":"1ea8cc9d-43fc-484e-8bd9-467b53d82f4a"}},"panels":{"center":["73","74","75","76","77","78","79"]},"incoming_content":null,"css_id":null,"context":[],"did":"13","renderer":"standard","layout":"flexible","layout_settings":[],"panel_settings":[],"cache":[],"title":"%node:title","hide_title":"0","title_pane":"73","uuid":"8914f91c-b456-4f63-a7b8-22ba91035943"}}},"cid":"0","last_comment_timestamp":"1397710081","last_comment_name":null,"last_comment_uid":"1","comment_count":"0","name":"webadmin","picture":"0","data":"a:3:{s:7:\"contact\";i:1;s:7:\"overlay\";i:1;s:25:\"overlay_message_dismissed\";i:1;}","num_revisions":"1","current_revision_id":"106678","is_current":true,"is_pending":false,"revision_moderation":false,"path":"http://transcripts.sl.nsw.gov.au/content/john-h-wheat-narrative-ca-1914-1918-page-13-1"}